combinational_circuit.v
module combinational_circuit (
    input wire [15:0] A, B, C, D,
    output wire out_signal
);

    wire [15:0] n1, n2, n3, n4, n5, n6, n7, n8, n9, n10;
    wire [15:0] n11, n12, n13, n14, n15, n16, n17, n18, n19, n20;

    Logic_Block1 U1 (.x(A[0]), .y(B[0]), .z(n1[0]), .w(n2[0]));
    Logic_Block2 U6 (.p(C[0]), .q(D[0]), .r(n11[0]), .s(n12[0]));

    and (n21[0], n1[0], n11[0]); 
    or  (n22[0], n2[0], n12[0]); 
    xor (n23[0], n21[0], n22[0]); 

    assign out_signal = ~n23[0]; 

endmodule

module Logic_Block1 (input wire x, y, output wire z, w);
    and (z, x, y);
    or  (w, x, y);
endmodule

module Logic_Block2 (input wire p, q, output wire r, s);
    xor (r, p, q);
    nand (s, p, q);
endmodule

testbench.v
`timescale 1ns / 1ps

module testbench;

    // Declare test signals
    reg [15:0] A, B, C, D;
    wire out_signal;

    // Instantiate the design under test (DUT)
    combinational_circuit uut (
        .A(A),
        .B(B),
        .C(C),
        .D(D),
        .out_signal(out_signal)
    );

    // Test Stimulus
    integer i;  // Loop variable

    initial begin
        $dumpfile("testbench.vcd");  // Dumps waveform data for GTKWave
        $dumpvars(0, testbench); 

        $display("🚀 Running Testbench with 60+ test cases...\n");

        // Apply 60+ test cases dynamically
        for (i = 0; i < 60; i = i + 1) begin
            A = $random;  // Generate random test values
            B = $random;
            C = $random;
            D = $random;
            #10;  // Delay of 10 time units
            $display("Test %0d | A: %h B: %h C: %h D: %h | Out: %h", i+1, A, B, C, D, out_signal);
        end

        $display("\n✅ Test completed with 60+ test cases.");
        $finish; // End simulation
    end

endmodule

testbench.vcd
$date
	Wed Feb 26 09:46:19 2025
$end
$version
	Icarus Verilog
$end
$timescale
	1ps
$end
$scope module testbench $end
$var wire 1 ! out_signal $end
$var reg 16 " A [15:0] $end
$var reg 16 # B [15:0] $end
$var reg 16 $ C [15:0] $end
$var reg 16 % D [15:0] $end
$var integer 32 & i [31:0] $end
$scope module uut $end
$var wire 16 ' A [15:0] $end
$var wire 16 ( B [15:0] $end
$var wire 16 ) C [15:0] $end
$var wire 16 * D [15:0] $end
$var wire 16 + n1 [15:0] $end
$var wire 16 , n11 [15:0] $end
$var wire 16 - n12 [15:0] $end
$var wire 16 . n2 [15:0] $end
$var wire 1 / n21 $end
$var wire 1 0 n22 $end
$var wire 1 1 n23 $end
$var wire 1 ! out_signal $end
$scope module U1 $end
$var wire 1 2 w $end
$var wire 1 3 x $end
$var wire 1 4 y $end
$var wire 1 5 z $end
$upscope $end
$scope module U6 $end
$var wire 1 6 p $end
$var wire 1 7 q $end
$var wire 1 8 r $end
$var wire 1 9 s $end
$upscope $end
$upscope $end
$upscope $end
$enddefinitions $end
#0
$dumpvars
09
08
17
16
05
14
03
12
11
10
0/
bz1 .
bz0 -
bz0 ,
bz0 +
b101011001100011 *
b1101011000001001 )
b101111010000001 (
b11010100100100 '
b0 &
b101011001100011 %
b1101011000001001 $
b101111010000001 #
b11010100100100 "
0!
$end
#10000
1!
01
1/
18
bz1 ,
19
bz1 -
15
bz1 +
bz1 .
07
13
b101001000010010 %
b101001000010010 *
b1000010001100101 $
b1000010001100101 )
b1001100110001101 #
b1001100110001101 (
b111101100001101 "
b111101100001101 '
b1 &
#20000
bz1 ,
bz1 -
17
06
b1100110100111101 %
b1100110100111101 *
b1111000101110110 $
b1111000101110110 )
b1100110100001101 #
b1100110100001101 (
b1110001100000001 "
b1110001100000001 '
b10 &
#30000
0!
11
0/
bz1 ,
bz1 -
05
bz0 +
bz1 .
07
16
04
b10010011000110 %
b10010011000110 *
b1110100111111001 $
b1110100111111001 )
b1111011110001100 #
b1111011110001100 (
b101011111101101 "
b101011111101101 '
b11 &
#40000
08
bz0 ,
09
bz0 -
17
b111001001110111 %
b111001001110111 *
b1111011111100101 $
b1111011111100101 )
b1101001010101010 #
b1101001010101010 (
b1000010011000101 "
b1000010011000101 '
b100 &
#50000
bz0 ,
19
bz1 -
bz0 +
bz1 .
07
06
14
03
b1001011011001110 %
b1001011011001110 *
b110100111110010 $
b110100111110010 )
b1101101110001111 #
b1101101110001111 (
b1101011000010010 "
b1101011000010010 '
b101 &
#60000
18
bz1 ,
bz1 -
17
b10100010111101 %
b10100010111101 *
b100100101011100 $
b100100101011100 )
b100111011000101 #
b100111011000101 (
b111101011101000 "
b111101011101000 '
b110 &
#70000
1!
01
1/
bz1 ,
bz1 -
15
bz1 +
bz1 .
07
16
13
b1000011100001010 %
b1000011100001010 *
b110001001100011 $
b110001001100011 )
b10011001100101 #
b10011001100101 (
b101100000101101 "
b101100000101101 '
b111 &
#80000
0!
11
0/
bz1 ,
bz1 -
05
bz0 +
02
bz0 .
17
06
04
03
b1100110010011101 %
b1100110010011101 *
b100010110101010 $
b100010110101010 )
b10000100100000 #
b10000100100000 (
b10001010000000 "
b10001010000000 '
b1000 &
#90000
08
bz0 ,
09
bz0 -
bz0 +
12
bz1 .
16
14
b1101011001010011 %
b1101011001010011 *
b11100000001101 $
b11100000001101 )
b1011100000010011 #
b1011100000010011 (
b11111010010110 "
b11111010010110 '
b1001 &
#100000
bz0 ,
19
bz1 -
15
bz1 +
bz1 .
07
06
13
b11111010101110 %
b11111010101110 *
b100101000000010 $
b100101000000010 )
b10101011010101 #
b10101011010101 (
b1101110101101011 "
b1101110101101011 '
b1010 &
#110000
1!
01
1/
18
bz1 ,
bz1 -
16
b110010100001010 %
b110010100001010 *
b100100100100011 $
b100100100100011 )
b111001011001111 #
b111001011001111 (
b1110100100011101 "
b1110100100011101 '
b1011 &
#120000
0!
11
0/
08
bz0 ,
bz1 -
05
bz0 +
02
bz0 .
06
04
03
b110000110001010 %
b110000110001010 *
b1011110111110010 $
b1011110111110010 )
b100110000111100 #
b100110000111100 (
b101011001010 "
b101011001010 '
b1100 &
#130000
18
bz1 ,
bz1 -
bz0 +
12
bz1 .
17
13
b1001010001001 %
b1001010001001 *
b1111001101111000 $
b1111001101111000 )
b11010011011000 #
b11010011011000 (
b1011001101000001 "
b1011001101000001 '
b1101 &
#140000
08
bz0 ,
bz1 -
07
b1001110101110 %
b1001110101110 *
b1111100111000110 $
b1111100111000110 )
b110010110110110 #
b110010110110110 (
b110111101011 "
b110111101011 '
b1110 &
#150000
1!
01
00
bz0 ,
09
bz0 -
bz0 +
02
bz0 .
17
16
03
b1011111001110001 %
b1011111001110001 *
b1001101000001011 $
b1001101000001011 )
b1101110100101010 #
b1101110100101010 (
b1010111100 "
b1010111100 '
b1111 &
#160000
1/
10
18
bz1 ,
19
bz1 -
15
bz1 +
12
bz1 .
07
14
13
b11001100111010 %
b11001100111010 *
b110000000111011 $
b110000000111011 )
b101010101001111 #
b101010101001111 (
b100000110000101 "
b100000110000101 '
b10000 &
#170000
0!
11
0/
08
bz0 ,
09
bz0 -
05
bz0 +
bz1 .
17
03
b100101111011001 %
b100101111011001 *
b1001101111110001 $
b1001101111110001 )
b100101100010101 #
b100101100010101 (
b11001001111110 "
b11001001111110 '
b10001 &
#180000
1!
01
00
bz0 +
02
bz0 .
04
b1010000110001111 %
b1010000110001111 *
b101010110011111 $
b101010110011111 )
b1111101101001100 #
b1111101101001100 (
b11101100010 "
b11101100010 '
b10010 &
#190000
0!
11
10
18
bz1 ,
19
bz1 -
bz0 +
12
bz1 .
07
14
b1001010001011100 %
b1001010001011100 *
b101011010011111 $
b101011010011111 )
b110000010110111 #
b110000010110111 (
b1010100111111000 "
b1010100111111000 '
b10011 &
#200000
1!
01
1/
15
bz1 +
bz1 .
13
b11111011010000 %
b11111011010000 *
b11001001001001 $
b11001001001001 )
b11011110001001 #
b11011110001001 (
b1100000001011011 "
b1100000001011011 '
b10100 &
#210000
0!
11
0/
08
bz0 ,
bz1 -
06
b111111100001100 %
b111111100001100 *
b10111110010110 $
b10111110010110 )
b1111110001010001 #
b1111110001010001 (
b1100000011010111 "
b1100000011010111 '
b10101 &
#220000
1!
01
00
bz0 ,
09
bz0 -
05
bz0 +
02
bz0 .
17
16
04
03
b1110110100111101 %
b1110110100111101 *
b101101001110111 $
b101101001110111 )
b1110110111001000 #
b1110110111001000 (
b1100111011000010 "
b1100111011000010 '
b10110 &
#230000
b1110011100111001 %
b1110011100111001 *
b1000000101101101 $
b1000000101101101 )
b1111110 #
b1111110 (
b1101101100010010 "
b1101101100010010 '
b10111 &
#240000
1/
10
18
bz1 ,
19
bz1 -
15
bz1 +
12
bz1 .
07
14
13
b1000100001111000 %
b1000100001111000 *
b10111110000101 $
b10111110000101 )
b1111011011010011 #
b1111011011010011 (
b1000111100011111 "
b1000111100011111 '
b11000 &
#250000
b1010111100101010 %
b1010111100101010 *
b1010111000111111 $
b1010111000111111 )
b100101101001001 #
b100101101001001 (
b101100101011011 "
b101100101011011 '
b11001 &
#260000
0!
11
0/
08
bz0 ,
bz1 -
05
bz0 +
02
bz0 .
06
04
03
b1111001010011100 %
b1111001010011100 *
b110010001110 $
b110010001110 )
b11100010000110 #
b11100010000110 (
b110001101011000 "
b110001101011000 '
b11010 &
#270000
1!
01
00
bz0 ,
09
bz0 -
17
16
b1011010010100011 %
b1011010010100011 *
b1011101110011 $
b1011101110011 )
b1011110000100110 #
b1011110000100110 (
b1001100111111010 "
b1001100111111010 '
b11011 &
#280000
1/
10
18
bz1 ,
19
bz1 -
15
bz1 +
12
bz1 .
07
14
13
b110101000100 %
b110101000100 *
b101011001011111 $
b101011001011111 )
b1001001010110011 #
b1001001010110011 (
b1010100000101111 "
b1010100000101111 '
b11100 &
#290000
0!
11
0/
08
bz0 ,
bz1 -
06
b1101101101011010 %
b1101101101011010 *
b1101011100110 $
b1101011100110 )
b11011011001011 #
b11011011001011 (
b1111110111110111 "
b1111110111110111 '
b11101 &
#300000
1!
01
1/
18
bz1 ,
bz1 -
17
b1011011001100101 %
b1011011001100101 *
b110110011011010 $
b110110011011010 )
b1110001011101101 #
b1110001011101101 (
b1100000100101001 "
b1100000100101001 '
b11110 &
#310000
bz1 ,
bz1 -
07
16
b1111111101000100 %
b1111111101000100 *
b1100101111001 $
b1100101111001 )
b1001010011011111 #
b1001010011011111 (
b1110001010110101 "
b1110001010110101 '
b11111 &
#320000
0!
11
0/
05
bz0 +
02
bz0 .
04
03
b1100111100001110 %
b1100111100001110 *
b1010110110101011 $
b1010110110101011 )
b101100101010 #
b101100101010 (
b110011010000 "
b110011010000 '
b100000 &
#330000
1!
01
00
08
bz0 ,
09
bz0 -
17
b1011000011 %
b1011000011 *
b111001011111101 $
b111001011111101 )
b1011110010011010 #
b1011110010011010 (
b1010110111011100 "
b1010110111011100 '
b100001 &
#340000
0!
11
10
18
bz1 ,
19
bz1 -
07
b11010000001010 %
b11010000001010 *
b111011001100111 $
b111011001100111 )
b1110100101001110 #
b1110100101001110 (
b1110110101010110 "
b1110110101010110 '
b100010 &
#350000
b1100010010111000 %
b1100010010111000 *
b1000011101111001 $
b1000011101111001 )
b1000101000111000 #
b1000101000111000 (
b1011100110110110 "
b1011100110110110 '
b100011 &
#360000
bz1 ,
bz1 -
bz0 +
12
bz1 .
17
06
14
b1100101001011001 %
b1100101001011001 *
b10110000000100 $
b10110000000100 )
b101110110010011 #
b101110110010011 (
b1011111110010100 "
b1011111110010100 '
b100100 &
#370000
08
bz0 ,
09
bz0 -
15
bz1 +
bz1 .
16
13
b10011001101101 %
b10011001101101 *
b1011011111011001 $
b1011011111011001 )
b1101111001001101 #
b1101111001001101 (
b110100111011011 "
b110100111011011 '
b100101 &
#380000
18
bz1 ,
19
bz1 -
05
bz0 +
02
bz0 .
06
04
03
b111000110010101 %
b111000110010101 *
b10110110110110 $
b10110110110110 )
b100100111001010 #
b100100111001010 (
b1110001001110110 "
b1110001001110110 '
b100110 &
#390000
1!
01
00
08
bz0 ,
09
bz0 -
16
b11101101001 %
b11101101001 *
b110000111110111 $
b110000111110111 )
b1001101100000100 #
b1001101100000100 (
b1101001000110 "
b1101001000110 '
b100111 &
#400000
0!
11
10
18
bz1 ,
19
bz1 -
06
b10000101101 %
b10000101101 *
b1101100100101000 $
b1101100100101000 )
b1000110110001000 #
b1000110110001000 (
b1011101010110100 "
b1011101010110100 '
b101000 &
#410000
08
bz0 ,
bz1 -
bz0 +
12
bz1 .
07
13
b100010100011100 %
b100010100011100 *
b1110010000001000 $
b1110010000001000 )
b1001110000101110 #
b1001110000101110 (
b11000011000111 "
b11000011000111 '
b101001 &
#420000
15
bz1 +
bz1 .
14
b110011110000110 %
b110011110000110 *
b1001000000011100 $
b1001000000011100 )
b11100101001 #
b11100101001 (
b1010011011111101 "
b1010011011111101 '
b101010 &
#430000
05
bz0 +
bz1 .
03
b1100010001110000 %
b1100010001110000 *
b1010011101100110 $
b1010011101100110 )
b1100011000111101 #
b1100011000111101 (
b100011011010 "
b100011011010 '
b101011 &
#440000
bz0 +
bz1 .
04
13
b111100111111010 %
b111100111111010 *
b1011001101011110 $
b1011001101011110 )
b1001100110111010 #
b1001100110111010 (
b10001110011 "
b10001110011 '
b101100 &
#450000
bz0 ,
09
bz0 -
17
16
b110000100110111 %
b110000100110111 *
b10111001 $
b10111001 )
b1111011000011010 #
b1111011000011010 (
b10111010101 "
b10111010101 '
b101101 &
#460000
bz0 ,
19
bz1 -
bz0 +
02
bz0 .
07
06
03
b1101010110110 %
b1101010110110 *
b1001111100100110 $
b1001111100100110 )
b10000111000000 #
b10000111000000 (
b11011110010110 "
b11011110010110 '
b101110 &
#470000
bz0 +
12
bz1 .
13
b1111111101111000 %
b1111111101111000 *
b101011110000110 $
b101011110000110 )
b111111011100 #
b111111011100 (
b1000001101111101 "
b1000001101111101 '
b101111 &
#480000
bz0 ,
09
bz0 -
bz0 +
bz1 .
17
16
14
03
b10101101111001 %
b10101101111001 *
b1011011011001111 $
b1011011011001111 )
b1000000011011011 #
b1000000011011011 (
b1001101101111110 "
b1001101101111110 '
b110000 &
#490000
b111100010100001 %
b111100010100001 *
b100100010111 $
b100100010111 )
b1110111001100001 #
b1110111001100001 (
b1110010011111010 "
b1110010011111010 '
b110001 &
#500000
1!
01
00
bz0 +
02
bz0 .
04
b1000100000110101 %
b1000100000110101 *
b101100111110101 $
b101100111110101 )
b1001011001010000 #
b1001011001010000 (
b1001000110000110 "
b1001000110000110 '
b110010 &
#510000
1/
10
18
bz1 ,
19
bz1 -
15
bz1 +
12
bz1 .
07
14
13
b1011010010011000 %
b1011010010011000 *
b111010011000101 $
b111010011000101 )
b111010111000001 #
b111010111000001 (
b1000101000101001 "
b1000101000101001 '
b110011 &
#520000
0!
11
0/
08
bz0 ,
bz1 -
06
b1011010001010 %
b1011010001010 *
b1110011011101100 $
b1110011011101100 )
b100001001110011 #
b100001001110011 (
b111101101001011 "
b111101101001011 '
b110100 &
#530000
1!
01
00
bz0 ,
09
bz0 -
05
bz0 +
02
bz0 .
17
16
04
03
b1000110010100001 %
b1000110010100001 *
b1111110110101001 $
b1111110110101001 )
b1000000010101000 #
b1000000010101000 (
b1101000101001110 "
b1101000101001110 '
b110101 &
#540000
0!
11
10
18
bz1 ,
19
bz1 -
07
b1011010100101010 %
b1011010100101010 *
b1100000010011111 $
b1100000010011111 )
b110011011100110 #
b110011011100110 (
b1011100100001110 "
b1011100100001110 '
b110110 &
#550000
08
bz0 ,
bz1 -
bz0 +
12
bz1 .
06
14
b1110011000111000 %
b1110011000111000 *
b1111111110011110 $
b1111111110011110 )
b1111010010001101 #
b1111010010001101 (
b1110100101010 "
b1110100101010 '
b110111 &
#560000
18
bz1 ,
bz1 -
bz0 +
bz1 .
17
04
13
b100000100010011 %
b100000100010011 *
b100010111001010 $
b100010111001010 )
b1110001111001000 #
b1110001111001000 (
b1010100001111001 "
b1010100001111001 '
b111000 &
#570000
08
bz0 ,
bz1 -
15
bz1 +
bz1 .
07
14
b1001110110111010 %
b1001110110111010 *
b1101110110110110 $
b1101110110110110 )
b1010111011000111 #
b1010111011000111 (
b1100100101101011 "
b1100100101101011 '
b111001 &
#580000
05
bz0 +
bz1 .
03
b1001101010110100 %
b1001101010110100 *
b1101001110010010 $
b1101001110010010 )
b1001010110111001 #
b1001010110111001 (
b1010101111000100 "
b1010101111000100 '
b111010 &
#590000
bz0 +
bz1 .
04
13
b1001010011110010 %
b1001010011110010 *
b1111010111111010 $
b1111010111111010 )
b1001000010000110 #
b1001000010000110 (
b11101101111111 "
b11101101111111 '
b111011 &
#600000
b111100 &
